{
  "elementId": 18205,
  "elementName": "Door",
  "elementType": "FamilyInstance",
  "category": "Specialty Equipment",
  "isVoid": false,
  "boundingBox": {
    "min": [
      5.354583333333318,
      -5.238835450315387,
      -4.263256414560601E-14
    ],
    "max": [
      8.374999999999996,
      -3.656250000000023,
      8.74999999999993
    ]
  },
  "meshes": [
    {
      "type": "solid",
      "volume": 2.0028249733094965,
      "surfaceArea": 50.16737290999412,
      "vertices": [
        [
          5.758881568908691,
          -3.65625,
          8.75
        ],
        [
          5.73934268951416,
          -3.6900923252105713,
          8.75
        ],
        [
          5.766406059265137,
          -3.7057173252105713,
          8.75
        ],
        [
          8.333333015441895,
          -5.238835334777832,
          8.75
        ],
        [
          8.375,
          -5.166666507720947,
          8.75
        ],
        [
          5.744278430938721,
          -3.7440438270568848,
          8.75
        ],
        [
          5.766406059265137,
          -3.7057173252105713,
          0.75
        ],
        [
          8.375,
          -5.166666507720947,
          0.75
        ],
        [
          8.333333015441895,
          -5.238835334777832,
          0.75
        ],
        [
          5.758881568908691,
          -3.65625,
          0.75
        ],
        [
          5.744278430938721,
          -3.7440438270568848,
          0.75
        ],
        [
          5.73934268951416,
          -3.6900923252105713,
          0.75
        ]
      ],
      "triangles": [
        [
          0,
          1,
          2
        ],
        [
          3,
          4,
          2
        ],
        [
          0,
          2,
          4
        ],
        [
          5,
          3,
          2
        ],
        [
          6,
          7,
          8
        ],
        [
          9,
          7,
          6
        ],
        [
          10,
          6,
          8
        ],
        [
          9,
          6,
          11
        ],
        [
          7,
          0,
          4
        ],
        [
          0,
          7,
          9
        ],
        [
          7,
          4,
          3
        ],
        [
          3,
          8,
          7
        ],
        [
          10,
          3,
          5
        ],
        [
          3,
          10,
          8
        ],
        [
          10,
          5,
          2
        ],
        [
          2,
          6,
          10
        ],
        [
          11,
          2,
          1
        ],
        [
          2,
          11,
          6
        ],
        [
          9,
          1,
          0
        ],
        [
          1,
          9,
          11
        ]
      ],
      "vertexCount": 12,
      "triangleCount": 20
    }
  ]
}